<?xml version="1.0" encoding="ISO-8859-1"?>
<DATA>
	<F_STEP>
		<RAD_F>40.000000</RAD_F>
		<RAD_L>20.000000</RAD_L>
		<RAD_R>20.000000</RAD_R>
		<FREE_F>60.00000</FREE_F>
		<FREE_L>0.00000</FREE_L>
		<FREE_R>0.00000</FREE_R>
		<OBST_F>0.00000</OBST_F>
		<OBST_L>20.00000</OBST_L>
		<OBST_R>20.00000</OBST_R>
	</F_STEP>
		<RAD_F>20.000000</RAD_F>
		<RAD_L>40.000000</RAD_L>
		<RAD_R>20.000000</RAD_R>
		<FREE_F>0.000000</FREE_F>
		<FREE_L>40.00000</FREE_L>
		<FREE_R>0.00000</FREE_R>
		<OBST_F>40.00000</OBST_F>
		<OBST_L>0.00000</OBST_L>
		<OBST_R>20.00000</OBST_R>	
	<L_STEP>
	</L_STEP>
	<R_STEP>
		<RAD_F>20.000000</RAD_F>
		<RAD_L>40.000000</RAD_L>
		<RAD_R>20.000000</RAD_R>
		<FREE_F>0.000000</FREE_F>
		<FREE_L>0.00000</FREE_L>
		<FREE_R>20.00000</FREE_R>
		<OBST_F>40.00000</OBST_F>
		<OBST_L>40.00000</OBST_L>
		<OBST_R>0.00000</OBST_R>	
	</R_STEP>
</DATA>
